lfd/__init__.py
lfd/lfd.py
lfd/3DAlignment/Bitmap.c
lfd/3DAlignment/Bitmap.h
lfd/3DAlignment/Circularity.c
lfd/3DAlignment/Circularity.h
lfd/3DAlignment/ColorDescriptor.c
lfd/3DAlignment/ColorDescriptor.h
lfd/3DAlignment/CompactColor.c
lfd/3DAlignment/Eccentricity.c
lfd/3DAlignment/Eccentricity.h
lfd/3DAlignment/FourierDescriptor.c
lfd/3DAlignment/FourierDescriptor.h
lfd/3DAlignment/Main.c
lfd/3DAlignment/Makefile
lfd/3DAlignment/Morphology.c
lfd/3DAlignment/Morphology.h
lfd/3DAlignment/RWObj.c
lfd/3DAlignment/RWObj.h
lfd/3DAlignment/RecovAffine.c
lfd/3DAlignment/RecovAffine.h
lfd/3DAlignment/Refine.c
lfd/3DAlignment/Refine.h
lfd/3DAlignment/RegionShape.c
lfd/3DAlignment/RegionShape.h
lfd/3DAlignment/Rotate.c
lfd/3DAlignment/Rotate.h
lfd/3DAlignment/Thin.c
lfd/3DAlignment/Thin.h
lfd/3DAlignment/TraceContour.c
lfd/3DAlignment/TraceContour.h
lfd/3DAlignment/TranslateScale.c
lfd/3DAlignment/TranslateScale.h
lfd/3DAlignment/TypeConverts.h
lfd/3DAlignment/convert.c
lfd/3DAlignment/convert.h
lfd/3DAlignment/ds.h
lfd/3DAlignment/edge.c
lfd/3DAlignment/edge.h
lfd/3DAlignment/glut.h
lfd/3DAlignment/fftw/config.c
lfd/3DAlignment/fftw/config.h
lfd/3DAlignment/fftw/executor.c
lfd/3DAlignment/fftw/f77_func.h
lfd/3DAlignment/fftw/fcr_1.c
lfd/3DAlignment/fftw/fcr_10.c
lfd/3DAlignment/fftw/fcr_11.c
lfd/3DAlignment/fftw/fcr_12.c
lfd/3DAlignment/fftw/fcr_128.c
lfd/3DAlignment/fftw/fcr_13.c
lfd/3DAlignment/fftw/fcr_14.c
lfd/3DAlignment/fftw/fcr_15.c
lfd/3DAlignment/fftw/fcr_16.c
lfd/3DAlignment/fftw/fcr_2.c
lfd/3DAlignment/fftw/fcr_3.c
lfd/3DAlignment/fftw/fcr_32.c
lfd/3DAlignment/fftw/fcr_4.c
lfd/3DAlignment/fftw/fcr_5.c
lfd/3DAlignment/fftw/fcr_6.c
lfd/3DAlignment/fftw/fcr_64.c
lfd/3DAlignment/fftw/fcr_7.c
lfd/3DAlignment/fftw/fcr_8.c
lfd/3DAlignment/fftw/fcr_9.c
lfd/3DAlignment/fftw/fftw-int.h
lfd/3DAlignment/fftw/fftw.h
lfd/3DAlignment/fftw/fftwf77.c
lfd/3DAlignment/fftw/fftwnd.c
lfd/3DAlignment/fftw/fhb_10.c
lfd/3DAlignment/fftw/fhb_16.c
lfd/3DAlignment/fftw/fhb_2.c
light_field_distance-0.0.9.dist-info/LICENSE
light_field_distance-0.0.9.dist-info/METADATA
light_field_distance-0.0.9.dist-info/WHEEL
light_field_distance-0.0.9.dist-info/top_level.txt
light_field_distance-0.0.9.dist-info/RECORD
